sampyling/__init__.py
sampyling-0.0.1.dist-info/LICENSE
sampyling-0.0.1.dist-info/METADATA
sampyling-0.0.1.dist-info/WHEEL
sampyling-0.0.1.dist-info/RECORD
