Metadata-Version: 2.1
Name: sampyling
Version: 0.0.1
Summary: samPYling, auxilia o desenvolvimento de amostras probabilísticas e estimações de uma população baseado em diversas técnicas de amostragem.
License: ALF
Author: Richard Wallan
Author-email: 3am.richardwallan@gmail.com
Requires-Python: ==3.11.*
Classifier: License :: OSI Approved :: Academic Free License (AFL)
Classifier: License :: Other/Proprietary License
Classifier: Natural Language :: Portuguese (Brazilian)
Classifier: Programming Language :: Python :: 3
Classifier: Programming Language :: Python :: 3.11
Classifier: Topic :: Education
Project-URL: Bug Tracker, https://github.com/samPYling/samPYling/issues
Project-URL: Código, https://github.com/samPYling/samPYling.git
Project-URL: Document, https://github.com/samPYling/samPYling/blob/main/README.md
